<?xml version="1.0" encoding="UTF-8"?>
<?xml-stylesheet href="hide-it.xsl" type="text/xsl"?>

<item>
<title>[COLORblue][B]Dates Shown Are Written In UK Format DD-MM-YYYY[/B][/COLOR]</title>
<link>ignoreme</link>
<thumbnail>https://i.imgur.com/r6nMlcQ.png</thumbnail>
<fanart></fanart>
</item>

<item>
<title>[COLORgold][B]*****All Links Are Free To Watch*****[/B][/COLOR]</title>
<link>ignoreme</link>
<thumbnail>https://i.imgur.com/r6nMlcQ.png</thumbnail>
<fanart></fanart>
</item>

<item>
<title>[COLORlime]>>> WWE Network <<<[/COLOR]</title>
<link>http://s1.mainevents.icu:8000/live/239021AM4884820/47212021AM4784345/448.m3u8</link>
<thumbnail>https://i.imgur.com/uZCTldR.png</thumbnail>
<fanart>https://i.imgur.com/wulr4GL.jpg</fanart>
</item>
  
<item>
<title>WWE Friday Night Smackdown 12-03-2021</title>
<link>https://streamsb.net/lkq395872414.html</link>
<thumbnail>https://i.imgur.com/YlG6aSU.jpg</thumbnail>
<fanart></fanart>
</item>
  
<item>
<title>WWE 205 Live 12-03-2021</title>
<link>https://streamsb.net/oprs13qqhyqr.html</link>
<thumbnail>https://i.imgur.com/tf0Qstm.jpg</thumbnail>
<fanart></fanart>
</item>
  
<item>
<title>WWE NXT 10-03-2021</title>
<link>https://streamsb.net/nxqxumft9nk0.html</link>
<thumbnail>https://i.imgur.com/t6K8GGX.png</thumbnail>
<fanart></fanart>
</item>

<item>
<title>AEW Dynamite 10-03-2021</title>
<link>https://streamsb.net/m7q2of90gxgx.html</link>
<thumbnail>https://i.imgur.com/9j1nbt0.jpg</thumbnail>
<fanart></fanart>
</item>
  
<item>
<title>AEW DARK 09-03-2021</title>
<link>https://streamsb.net/27mgnmwwfmf1.html</link>
<thumbnail>https://i.imgur.com/bRWA2CJ.png</thumbnail>
<fanart></fanart>
</item>
  
<item>
<title>Impact Wrestling 09-03-2021</title>
<link>https://streamsb.net/jki00c3y8kc8.html</link>
<thumbnail>https://i.imgur.com/pOdXDg6.jpg</thumbnail>
<fanart></fanart>
</item>
  
<item>
<title>WWE Monday Night Raw 08-03-2021</title>
<link>https://streamsb.net/loz8ys0h273m.html</link>
<thumbnail>https://i.imgur.com/LD14wVD.jpg</thumbnail>
<fanart></fanart>
</item>
  
<item>
<title>AEW Revolution 07-03-2021</title>
<link>https://streamtape.com/v/wrPXRL4RbqSJZAG/AEW_Revolution_2021_PPV_720p_WEB_h264-DaShield%5Beztv.re%5D.mp4</link>
<thumbnail>https://i.imgur.com/bHqHgMa.jpg</thumbnail>
<fanart></fanart>
</item>
  
<item>
<title>AEW Revolution The Buy In 07-03-2021</title>
<link>https://streamtape.com/v/Kw76VpAbe2F09kY/AEW.Revolution.2021.The.Buy.In.FITE.720p.WEBRip.h264-TJ.mp4</link>
<thumbnail>https://i.imgur.com/bHqHgMa.jpg</thumbnail>
<fanart></fanart>
</item>
  
<item>
<title>UFC 259 Jan Blakhovich vs Israel Adesanya</title>
<link>https://streamtape.com/v/3oxWmOZ9mWude4O/video_2021-03-07_14-37-50.mp4</link>
<thumbnail>https://i.imgur.com/mwdL4WX.jpg</thumbnail>
<fanart></fanart>
</item>
  
<item>
<title>UFC 259 Islam Makhachev vs Drew Dober</title>
<link>https://streamtape.com/v/Kwek1BoPyrF0QWY/video_2021-03-07_14-37-46.mp4</link>
<thumbnail>https://i.imgur.com/mwdL4WX.jpg</thumbnail>
<fanart></fanart>
</item>
  
<item>
<title>UFC 259 Peter Jan vs Aljamain Sterling</title>
<link>https://streamtape.com/v/qjyq2BjMprSzp2o/video_2021-03-07_14-37-40.mp4</link>
<thumbnail>https://i.imgur.com/mwdL4WX.jpg</thumbnail>
<fanart></fanart>
</item>
  
<item>
<title>UFC 259 Main Card</title>
<link>https://streamtape.com/v/Wr2wwYopmJTbx4K/UFC.259.540p.HDTV.H264.Fight-BB.mkv.mp4</link>
<thumbnail>https://i.imgur.com/mwdL4WX.jpg</thumbnail>
<fanart></fanart>
</item>
  
<item>
<title>UFC 259 Prelims</title>
<link>https://streamtape.com/v/AAXby8oP7vsXyDK/UFC.259.Prelims.WEB-DL.H264.Fight-BB.mp4</link>
<thumbnail>https://i.imgur.com/mwdL4WX.jpg</thumbnail>
<fanart></fanart>
</item>
  
<item>
<title>UFC 259 Early Prelims</title>
<link>https://streamtape.com/v/DeBd1km8bRFVrZ/UFC.259.Early.Prelims.WEB-DL.H264.Fight-BB.mp4</link>
<thumbnail>https://i.imgur.com/mwdL4WX.jpg</thumbnail>
<fanart></fanart>
</item>
  
<item>
<title>AEW DARK 06-03-2021</title>
<link>https://aparat.cam/wng9g0ly4nbw/AEW.DARK.6th.March.2021.WEBRip.h264-TJ.mp4.html</link>
<thumbnail>https://i.imgur.com/bRWA2CJ.png</thumbnail>
<fanart></fanart>
</item>
  
<item>
<title>WWE Friday Night Smackdown 05-03-2021</title>
<link>https://streamtape.com/v/xrpbqPKr2WTk67M/WWE.Friday.Night.Smackdown.2021.03.05.HDTV.x264-SkY.mp4</link>
<thumbnail>https://i.imgur.com/YlG6aSU.jpg</thumbnail>
<fanart></fanart>
</item>
  
<item>
<title>WWE 205 Live 05-03-2021</title>
<link>https://aparat.cam/u6wvss7dm1xz/WWE.205.Live.2021.03.05.720p.Lo.WEB.h264-HEEL.mp4.html</link>
<thumbnail>https://i.imgur.com/tf0Qstm.jpg</thumbnail>
<fanart></fanart>
</item>

<item>
<title>WWE NXT 03-03-2021</title>
<link>https://aparat.cam/91pzic32qfla/WWE.NXT.3rd.March.2021.WEBRip.h264-TJ.mp4.html</link>
<thumbnail>https://i.imgur.com/t6K8GGX.png</thumbnail>
<fanart></fanart>
</item>

<item>
<title>AEW Dynamite 03-03-2021</title>
<link>https://aparat.cam/uijisibj7ajh/AEW.Dynamite.2021.03.03.720p.WEB.h264-HEEL.mp4.html</link>
<thumbnail>https://i.imgur.com/9j1nbt0.jpg</thumbnail>
<fanart></fanart>
</item>

<item>
<title>AEW DARK 02-03-2021</title>
<link>https://aparat.cam/ro9hf5nomksf/AEW.DARK.2nd.March.2021.720p.WEBRip.h264-TJ.mp4.html</link>
<thumbnail>https://i.imgur.com/bRWA2CJ.png</thumbnail>
<fanart></fanart>
</item>

<item>
<title>WWE Monday Night Raw 01-03-2021</title>
<link>https://aparat.cam/lmlw48mx6h1y/WWE.Monday.Night.Raw.2021.03.01.HDTV.x264-NWCHD.mp4.html</link>
<thumbnail>https://i.imgur.com/LD14wVD.jpg</thumbnail>
<fanart></fanart>
</item>

<item>
<title>WWE Monday Night Raw 01-03-2021</title>
<link>https://streamtape.com/v/A4pZjYz3XWhXKPj/WWE.Monday.Night.Raw.2021.03.01.HDTV.x264-NWCHD.mp4</link>
<thumbnail>https://i.imgur.com/LD14wVD.jpg</thumbnail>
<fanart></fanart>
</item>

<item>
<title>AEW Women's World Championship Eliminator Tournament Show 4 1-03-2021</title>
<link>https://aparat.cam/2ove598w16wf/AEW.Womens.World.Championship.Eliminator.Tournament.Show.4.1st.March.2021.720p.WEBRip.h264-TJ.mp4.html</link>
<thumbnail>https://i.imgur.com/pgIbVpM.jpg</thumbnail>
<fanart></fanart>
</item>

<item>
<title>WWE Talking Smack 27-02-2021</title>
<link>https://aparat.cam/v3v0lun4jf5m/WWE.Talking.Smack.27th.Feb.2021.720p.WEBRip.h264-TJ.mp4.html</link>
<thumbnail>https://i.imgur.com/DdCbYWL.png</thumbnail>
<fanart></fanart>
</item>

<item>
<title>Bruno v Tyson (2021)</title>
<link>https://aparat.cam/qbok6fv91luz/Bruno.V.Tyson.2021.720p.BluRay.x264.AAC-_5BYTS.MX_5D.mp4.html</link>
<thumbnail>https://i.imgur.com/DUSZUtW.jpg</thumbnail>
<fanart></fanart>
</item>

<item>
<title>UFC Fight Night Rozenstruik Vs Gane Main Card</title>
<link>https://aparat.cam/zhlu5lvwnjfr/UFC.Fight.Night.Rozenstruik.vs.Gane.WEB-DL.H264.Fight-BB.mp4.html</link>
<thumbnail>https://i.imgur.com/FG3pfm5.jpg</thumbnail>
<fanart></fanart>
</item>

<item>
<title>UFC Fight Night Rozenstruik Vs Gane Main Card</title>
<link>https://streamtape.com/v/kLXblYKdbYiOvQy/UFC.Fight.Night.Rozenstruik.vs.Gane.WEB-DL.H264.Fight-BB.mp4</link>
<thumbnail>https://i.imgur.com/FG3pfm5.jpg</thumbnail>
<fanart></fanart>
</item>

<item>
<title>UFC Fight Night Rozenstruik Vs Gane Prelims</title>
<link>https://aparat.cam/1jkjn6f75oog/UFC.Fight.Night.Rozenstruik.vs.Gane.Prelims.WEB-DL.H264.Fight-BB__5BA1Rip.com_5D.mp4.html</link>
<thumbnail>https://i.imgur.com/FG3pfm5.jpg</thumbnail>
<fanart></fanart>
</item>

<item>
<title>UFC Fight Night Rozenstruik Vs Gane Prelims</title>
<link>https://streamtape.com/v/MYDLqY30GYTe9Y/UFC.Fight.Night.Rozenstruik.vs.Gane.Prelims.WEB-DL.H264.Fight-BB_%5BA1Rip.com%5D.mp4</link>
<thumbnail>https://i.imgur.com/FG3pfm5.jpg</thumbnail>
<fanart></fanart>
</item>

<item>
<title>WWE Friday Night Smackdown 26-02-2021</title>
<link>https://aparat.cam/6koaanipgvlq/WWE.Friday.Night.SmackDown.2021.02.26.HDTV.x264-NWCHD.mp4.html</link>
<thumbnail>https://i.imgur.com/YlG6aSU.jpg</thumbnail>
<fanart></fanart>
</item>

<item>
<title>WWE Friday Night Smackdown 26-02-2021</title>
<link>https://streamtape.com/v/BGwpWD0weMTykQv/WWE.Friday.Night.SmackDown.2021.02.26.HDTV.x264-NWCHD.mp4</link>
<thumbnail>https://i.imgur.com/YlG6aSU.jpg</thumbnail>
<fanart></fanart>
</item>

<item>
<title>WWE NXT UK 25-02-2021</title>
<link>https://aparat.cam/gtisp7ghh5ab/WWE.NXT.UK.2021.02.25.720p.Lo.WEB.h264-HEEL_5Beztv.re_5D.mp4.html</link>
<thumbnail>https://i.imgur.com/QCTdAkr.jpg</thumbnail>
<fanart></fanart>
</item>

<item>
<title>WWE NXT 24-02-2021</title>
<link>https://streamtape.com/v/ywazJvd3bAt1qX7/WWE.NXT.24th.Feb.2021.WEBRip.h264-TJ.mp4</link>
<thumbnail>https://i.imgur.com/t6K8GGX.png</thumbnail>
<fanart></fanart>
</item>

<item>
<title>AEW Dynamite 24-02-2021</title>
<link>https://streamtape.com/v/vxzkKYWrwQi4gp1/AEW.Dynamite.2021.02.24.720p.WEB.h264-HEEL.mp4</link>
<thumbnail>https://i.imgur.com/9j1nbt0.jpg</thumbnail>
<fanart></fanart>
</item>

<item>
<title>AEW DARK 23-02-2021</title>
<link>https://streamtape.com/v/jWJM7OX19xFqeQ/AEW.DARK.23rd.Feb.2021.WEBRip.h264-TJ.mp4</link>
<thumbnail>https://i.imgur.com/bRWA2CJ.png</thumbnail>
<fanart></fanart>
</item>

<item>
<title>Impact Wrestling 23-02-2021</title>
<link>https://aparat.cam/a66hdfuo2zd3/iMPACT.Wrestling.2021.02.23.HDTV.x264-NWCHD.mp4.html</link>
<thumbnail>https://i.imgur.com/pOdXDg6.jpg</thumbnail>
<fanart></fanart>
</item>

<item>
<title>AEW Women's World Championship Eliminator Tournament Show 2 22-02-2021</title>
<link>https://aparat.cam/9jidh36ehx3u/AEW.Womens.World.Championship.Eliminator.Tournament.Show.2.22nd.Feb.2021.720p.WEBRip.h264-TJ.mp4.html</link>
<thumbnail>https://i.imgur.com/KdlHZ4h.jpg</thumbnail>
<fanart></fanart>
</item>

<item>
<title>WWE Monday Night Raw 22-02-2021</title>
<link>https://aparat.cam/41syb021444k/WWE.Monday.Night.Raw.2021.02.22.HDTV.x264-NWCHD.mp4.html</link>
<thumbnail>https://i.imgur.com/LD14wVD.jpg</thumbnail>
<fanart></fanart>
</item>

<item>
<title>WWE Monday Night Raw 22-02-2021</title>
<link>https://streamsb.net/vmsush9sqyuw.html</link>
<thumbnail>https://i.imgur.com/LD14wVD.jpg</thumbnail>
<fanart></fanart>
</item>

<item>
<title>WWE Elimination Chamber 21-02-2021</title>
<link>https://aparat.cam/srwbwlq8quvk/WWE.Elimination.Chamber.2021.PPV.WEB.h264-HEEL.mp4.html</link>
<thumbnail>https://i.imgur.com/0yb4YI7.jpg</thumbnail>
<fanart></fanart>
</item>

<item>
<title>WWE Elimination Chamber 21-02-2021</title>
<link>https://streamsb.net/nknf6yf0l4v0.html</link>
<thumbnail>https://i.imgur.com/0yb4YI7.jpg</thumbnail>
<fanart></fanart>
</item>

<item>
<title>Piers Morgans Life Stories S12E05 Chris Eubank</title>
<link>https://streamtape.com/v/qloo38W6qRi1gQ/Piers.Morgans.Life.Stories.S12E05.Chris.Eubank.480p.x264-mSD%5Beztv.re%5D.mkv.mp4</link>
<thumbnail></thumbnail>
<fanart></fanart>
</item>

<item>
<title>UFC Fight Night Blaydes vs Lewis</title>
<link>https://aparat.cam/xj4qihv5co7y/UFC.Fight.Night.Blaydes.vs.Lewis.WEB-DL.H264.Fight-BB.mp4.html</link>
<thumbnail>https://i.imgur.com/BjIInK0.jpg</thumbnail>
<fanart></fanart>
</item>

<item>
<title>UFC Fight Night Blaydes vs Lewis</title>
<link>https://streamsb.net/e7a1s7sdcsr2.html</link>
<thumbnail>https://i.imgur.com/BjIInK0.jpg</thumbnail>
<fanart></fanart>
</item>

<item>
<title>UFC Fight Night Blaydes vs Lewis Prelims</title>
<link>https://aparat.cam/py9309nr0j7s/UFC.Fight.Night.Blaydes.vs.Lewis.Prelims.WEB-DL.H264.Fight-BB.mp4.html</link>
<thumbnail>https://i.imgur.com/BjIInK0.jpg</thumbnail>
<fanart></fanart>
</item>

<item>
<title>UFC Fight Night Blaydes vs Lewis Prelims</title>
<link>https://streamsb.net/5b8kkauh1k0y.html</link>
<thumbnail>https://i.imgur.com/BjIInK0.jpg</thumbnail>
<fanart></fanart>
</item>

<item>
<title>WWE Friday Night Smackdown 19-02-2021</title>
<link>https://streamsb.net/zwi2dalslmdv.html</link>
<thumbnail>https://i.imgur.com/YlG6aSU.jpg</thumbnail>
<fanart></fanart>
</item>

<item>
<title>WWE Friday Night Smackdown 19-02-2021</title>
<link>https://aparat.cam/yvfj19iqhwry/WWE.Friday.Night.SmackDown.2021.02.19.HDTV.x264-NWCHD.mp4.html</link>
<thumbnail>https://i.imgur.com/YlG6aSU.jpg</thumbnail>
<fanart></fanart>
</item>
  
<item>
<title>WWE 205 Live 19-02-2021</title>
<link>https://aparat.cam/f3wjorwhcry3/WWE.205.Live.2021.02.19.720p.Lo.WEB.h264-HEEL.mp4.html</link>
<thumbnail>https://i.imgur.com/tf0Qstm.jpg</thumbnail>
<fanart></fanart>
</item>

<item>
<title>WWE NXT 17-02-2021</title>
<link>https://aparat.cam/rpoplk760f02/WWE.NXT.2021.02.17.HDTV.x264-Star.mp4.html</link>
<thumbnail>https://i.imgur.com/t6K8GGX.png</thumbnail>
<fanart></fanart>
</item>

<item>
<title>AEW Dynamite 17-02-2021</title>
<link>https://streamsb.net/kdifwfia4qtj.html</link>
<thumbnail>https://i.imgur.com/9j1nbt0.jpg</thumbnail>
<fanart></fanart>
</item>

<item>
<title>AEW Dynamite 17-02-2021</title>
<link>https://streamtape.com/v/XYz6YJXPdacWpx/AEW.Dynamite.2021.02.17.HDTV.x264-NWCHD.mp4</link>
<thumbnail>https://i.imgur.com/9j1nbt0.jpg</thumbnail>
<fanart></fanart>
</item>

<item>
<title>Impact Wrestling 16-02-2021</title>
<link>https://streamsb.net/917t3p0nxcyb.html</link>
<thumbnail>https://i.imgur.com/pOdXDg6.jpg</thumbnail>
<fanart></fanart>
</item>

<item>
<title>AEW DARK 16-02-2021</title>
<link>https://aparat.cam/e5ntj21dcpnf/AEW.DARK.16th.Feb.2021.720p.WEBRip.h264-TJ.mp4.html</link>
<thumbnail>https://i.imgur.com/bRWA2CJ.png</thumbnail>
<fanart></fanart>
</item>

<item>
<title>WWE Monday Night Raw 15-02-2021</title>
<link>https://aparat.cam/5h53n1wc4iub/WWE.Monday.Night.Raw.2021.02.15.HDTV.x264-NWCHD.mp4.html</link>
<thumbnail>https://i.imgur.com/LD14wVD.jpg</thumbnail>
<fanart></fanart>
</item>

<item>
<title>WWE Raw Talk 15-02-2021</title>
<link>https://aparat.cam/eohg8ktqehil/WWE.RAW.Talk.15th.Feb.2021.720p.WEBRip.h264-TJ.mp4.html</link>
<thumbnail>https://i.imgur.com/IHaUNM3.jpg</thumbnail>
<fanart></fanart>
</item>

<item>
<title>WWE NXT TakeOver - Vengeance Day 14-02-2021</title>
<link>https://aparat.cam/cmq3u8xcmx52/WWE.NXT.TakeOver.Vengeance.Day.2021.WEB.h264-HEEL.mp4.html</link>
<thumbnail>https://i.imgur.com/LZcdEG9.jpg</thumbnail>
<fanart></fanart>
</item>

<item>
<title>WWE NXT TakeOver - Vengeance Day 14-02-2021</title>
<link>https://streamsb.net/9ir7jn6k3nvk.html</link>
<thumbnail>https://i.imgur.com/LZcdEG9.jpg</thumbnail>
<fanart></fanart>
</item>

<item>
<title>Boxing Josh Warrington vs Mauricio Lara</title>
<link>https://aparat.cam/riawyva9seq2/Boxing.2021.02.13.Josh.Warrington.vs.Mauricio.Lara.480p.x264-mSD.mkv.html</link>
<thumbnail>https://i.imgur.com/Yk71dCw.png</thumbnail>
<fanart></fanart>
</item>

<item>
<title>FULL CARD HIGHLIGHTS | Diaz vs. Rakhimov</title>
<link>https://youtu.be/YcLEmU4wJ9o</link>
<thumbnail>https://i.imgur.com/gXwuuZ6.jpg</thumbnail>
<fanart></fanart>
</item>

<item>
<title>Impact Wrestling No Surrender 13-02-2021</title>
<link>https://aparat.cam/vrvhesakjapd/iMPACT.Wrestling.No.Surrender.2021.WEBRip.h264-TJ.mp4.html</link>
<thumbnail>https://i.imgur.com/lRXQoTD.jpg</thumbnail>
<fanart></fanart>
</item>

<item>
<title>UFC 258 Main Fight</title>
<link>https://aparat.cam/x1yfrn0hj4dl/video_2021-02-14_11-32-20.mp4.html</link>
<thumbnail>https://i.imgur.com/LlNajDL.jpg</thumbnail>
<fanart></fanart>
</item>

<item>
<title>UFC 258 Main Card</title>
<link>https://aparat.cam/wkdh8aseoqv5/UFC.258.PPV.Usman.vs.Burns.HDTV.x264-PUNCH.mkv.html</link>
<thumbnail>https://i.imgur.com/LlNajDL.jpg</thumbnail>
<fanart></fanart>
</item>

<item>
<title>UFC 258 Prelims</title>
<link>https://streamtape.com/v/laorKkMdlGt7GjQ/UFC.258.Prelims.WEB-DL.H264.Fight-BB.mp4</link>
<thumbnail>https://i.imgur.com/LlNajDL.jpg</thumbnail>
<fanart></fanart>
</item>

<item>
<title>UFC 258 Early Prelims</title>
<link>https://aparat.cam/5vis9vqj1w21/UFC.258.Early.Prelims.720p.WEB-DL.H264.Fight-BB.mp4.html</link>
<thumbnail>https://i.imgur.com/LlNajDL.jpg</thumbnail>
<fanart></fanart>
</item>

<item>
<title>WWE Friday Night Smackdown 12-02-2021</title>
<link>https://aparat.cam/lc517vx9jch6/WWE.Friday.Night.SmackDown.12th.Feb.2021.WEBRip.h264-TJ.mp4.html</link>
<thumbnail>https://i.imgur.com/YlG6aSU.jpg</thumbnail>
<fanart></fanart>
</item>
  
<item>
<title>WWE 205 Live 12-02-2021</title>
<link>https://aparat.cam/8duyocy4dtik/WWE.205.Live.2021.02.12.720p.Lo.WEB.h264-HEEL.mp4.html</link>
<thumbnail>https://i.imgur.com/tf0Qstm.jpg</thumbnail>
<fanart></fanart>
</item>

<item>
<title>WWE NXT UK 11-02-2021</title>
<link>https://streamtape.com/v/1Jxmjw0RyMIe2Qe/WWE.NXT.UK.2021.02.11.720p.Lo.WEB.h264-HEEL.mp4</link>
<thumbnail>https://i.imgur.com/QCTdAkr.jpg</thumbnail>
<fanart></fanart>
</item>

<item>
<title>WWE NXT 10-02-2021</title>
<link>https://aparat.cam/enpacpdeoaj8/WWE.NXT.2021.02.10.HDTV.x264-Star.mp4.html</link>
<thumbnail>https://i.imgur.com/t6K8GGX.png</thumbnail>
<fanart></fanart>
</item>

<item>
<title>AEW Dynamite 10-02-2021</title>
<link>https://streamtape.com/v/bP286dza1gcPppl/AEW.Dynamite.2021.02.10.720p.WEB.h264-HEEL.mp4</link>
<thumbnail>https://i.imgur.com/9j1nbt0.jpg</thumbnail>
<fanart></fanart>
</item>

<item>
<title>AEW DARK 09-02-2021</title>
<link>https://aparat.cam/vaw6cmv1h500/AEW.DARK.9th.Feb.2021.WEBRip.h264-TJ.mp4.html</link>
<thumbnail>https://i.imgur.com/bRWA2CJ.png</thumbnail>
<fanart></fanart>
</item>

<item>
<title>iMPACT Wrestling 09-02-2021</title>
<link>https://aparat.cam/vjttayrj4ty3/iMPACT.Wrestling.2021.02.09.HDTV.x264-NWCHD.mp4.html</link>
<thumbnail>https://i.imgur.com/nXBS1GK.jpg</thumbnail>
<fanart></fanart>
</item>

<item>
<title>WWE Monday Night Raw 08-02-2021</title>
<link>https://aparat.cam/czp77zdpy5el/WWE.Monday.Night.Raw.2021.02.08.HDTV.x264-NWCHD.mp4.html</link>
<thumbnail>https://i.imgur.com/LD14wVD.jpg</thumbnail>
<fanart></fanart>
</item>

<item>
<title>UFC Fight Night 184 Main Fight</title>
<link>https://aparat.cam/pnpzm1vpudcg/video_2021-02-07_09-37-20.mp4.html</link>
<thumbnail>https://i.imgur.com/FIQm6dp.jpg</thumbnail>
<fanart></fanart>
</item>

<item>
<title>UFC Fight Night 184 Main Card</title>
<link>https://streamtape.com/v/RpLwYJBGxOtLDb/UFC.Fight.Night.184.Overeem.vs.Volkov.HDTV.x264-PUNCH.mkv.mp4</link>
<thumbnail>https://i.imgur.com/FIQm6dp.jpg</thumbnail>
<fanart></fanart>
</item>

<item>
<title>UFC Fight Night 184 Prelims</title>
<link>https://aparat.cam/67gv7xy5lgbt/UFC.Fight.Night.184.Prelims.FP.WEB-DL.H264-SHREDDiE.mp4.html</link>
<thumbnail>https://i.imgur.com/FIQm6dp.jpg</thumbnail>
<fanart></fanart>
</item>

<item>
<title>One Championship - Unbreakable III 05-02-2021</title>
<link>https://streamtape.com/v/pazV4Laql8tryD6/One.Championship.Unbreakable.III.720p.WEBRip.h264-TJ.mp4</link>
<thumbnail>https://i.imgur.com/qY72Hgq.jpg</thumbnail>
<fanart></fanart>
</item>
  
<item>
<title>WWE Friday Night Smackdown 05-02-2021</title>
<link>https://aparat.cam/r4uxi7mce4ce/WWE.Friday.Night.SmackDown.2021.02.05.HDTV.x264-NWCHD.mp4.html</link>
<thumbnail>https://i.imgur.com/YlG6aSU.jpg</thumbnail>
<fanart></fanart>
</item>
  
<item>
<title>WWE 205 Live 05-02-2021</title>
<link>https://aparat.cam/awbjq05ibf0d/WWE.205.Live.2021.02.05.720p.Lo.WEB.h264-HEEL.mp4.html</link>
<thumbnail>https://i.imgur.com/tf0Qstm.jpg</thumbnail>
<fanart></fanart>
</item>
  
<item>
<title>WWE NXT UK 04-02-2021</title>
<link>https://aparat.cam/9ot9q6idfrur/WWE.NXT.UK.2021.02.04.WWE.Network.HDTV.x264-Star_5Beztv.re_5D.mp4.html</link>
<thumbnail>https://i.imgur.com/QCTdAkr.jpg</thumbnail>
<fanart></fanart>
</item>

<item>
<title>WWE NXT 03-02-2021</title>
<link>https://aparat.cam/awnxb85rloxg/WWE.NXT.3rd.Feb.2021.720p.WEBRip.h264-TJ.mp4.html</link>
<thumbnail>https://i.imgur.com/t6K8GGX.png</thumbnail>
<fanart></fanart>
</item>

<item>
<title>AEW Dynamite 03-02-2021</title>
<link>https://aparat.cam/oopvclk2xj7w/AEW.Dynamite.2021.02.03.720p.WEB.h264-HEEL.mp4.html</link>
<thumbnail>https://i.imgur.com/9j1nbt0.jpg</thumbnail>
<fanart></fanart>
</item>

<item>
<title>iMPACT Wrestling 02-02-2021</title>
<link>https://aparat.cam/1dou5oaissx9/iMPACT.Wrestling.2021.02.02.HDTV.x264-NWCHD.mp4.html</link>
<thumbnail>https://i.imgur.com/nXBS1GK.jpg</thumbnail>
<fanart></fanart>
</item>

<item>
<title>AEW DARK 02-02-2021</title>
<link>https://aparat.cam/zgqb0i5cealz/AEW.DARK.2nd.Feb.2021.720p.WEBRip.h264-TJ.mp4.html</link>
<thumbnail>https://i.imgur.com/bRWA2CJ.png</thumbnail>
<fanart></fanart>
</item>

<item>
<title>WWE Monday Night Raw 01-02-2021</title>
<link>https://aparat.cam/8517q0k764p9/WWE.Monday.Night.Raw.2021.02.01.HDTV.x264-NWCHD.mp4.html</link>
<thumbnail>https://i.imgur.com/LD14wVD.jpg</thumbnail>
<fanart></fanart>
</item>

<item>
<title>WWE Royal Rumble 31st January 2021</title>
<link>https://streamtape.com/v/Oq79Lk6wXqSZJBz/WWE.Royal.Rumble.2021.WEB.h264-DaShield.mp4</link>
<thumbnail>https://i.imgur.com/isyaOap.jpg</thumbnail>
<fanart></fanart>
</item>

<item>
<title>WWE Royal Rumble 31st January 2021</title>
<link>https://aparat.cam/4iqgg35zycqf/WWE.Royal.Rumble.2021.PPV.WEB.h264-HEEL.mp4.html</link>
<thumbnail>https://i.imgur.com/isyaOap.jpg</thumbnail>
<fanart></fanart>
</item>

<item>
<title>WWE Royal Rumble Kickoff 31st January 2021</title>
<link>https://aparat.cam/jstfh8wwt1hv/WWE.Royal.Rumble.2021.Kickoff.720p.WEBRip.h264-TJ.mp4.html</link>
<thumbnail>https://i.imgur.com/ms1cw88.jpg</thumbnail>
<fanart></fanart>
</item>

<item>
<title>WWE Friday Night Smackdown 29-01-2021</title>
<link>https://aparat.cam/cd1l3nig7dvu/WWE.Friday.Night.SmackDown.2021.01.29.HDTV.x264-NWCHD.mp4.html</link>
<thumbnail>https://i.imgur.com/YlG6aSU.jpg</thumbnail>
<fanart></fanart>
</item>

<item>
<title>WWE NXT UK 28-01-2021</title>
<link>https://aparat.cam/qlkqked5safn/WWE.NXT.UK.2021.01.28.720p.Lo.WEB.h264-HEEL.mp4.html</link>
<thumbnail>https://i.imgur.com/QCTdAkr.jpg</thumbnail>
<fanart></fanart>
</item>

<item>
<title>WWE NXT 27-01-2021</title>
<link>https://aparat.cam/ugwfzqvyci04/WWE.NXT.2021.01.27.HDTV.x264-Star.mp4.html</link>
<thumbnail>https://i.imgur.com/t6K8GGX.png</thumbnail>
<fanart></fanart>
</item>

<item>
<title>AEW DARK 26-01-2021</title>
<link>https://aparat.cam/7zogzgdlkv3r/AEW.DARK.26th.Jan.2021.720p.WEBRip.h264-TJ.mp4.html</link>
<thumbnail>https://i.imgur.com/bRWA2CJ.png</thumbnail>
<fanart></fanart>
</item>

<item>
<title>WWE Monday Night Raw 25-01-2021</title>
<link>https://aparat.cam/2r71cp56zci0/WWE.Monday.Night.Raw.2021.01.25.HDTV.x264-NWCHD.mp4.html</link>
<thumbnail>https://i.imgur.com/LD14wVD.jpg</thumbnail>
<fanart></fanart>
</item>

<item>
<title>UFC 257 Main Event</title>
<link>https://aparat.cam/sgu8szbx7f0q/video_2021-01-24_06-02-42.mp4.html</link>
<thumbnail>https://i.imgur.com/ztwIAR2.jpg</thumbnail>
<fanart></fanart>
</item>

<item>
<title>UFC 257 Full Main Card</title>
<link>https://streamtape.com/v/jvqdzaGqarIz8my/UFC.257.PPV.Poirier.vs.McGregor.HDTV.x264-NOGGINS.mkv.mp4</link>
<thumbnail>https://i.imgur.com/ztwIAR2.jpg</thumbnail>
<fanart></fanart>
</item>

<item>
<title>UFC 257 Prelims</title>
<link>https://aparat.cam/z0ex1avhj976/UFC.257.Prelims.WEB-DL.H264.Fight-BB.mp4.html</link>
<thumbnail>https://i.imgur.com/ztwIAR2.jpg</thumbnail>
<fanart></fanart>
</item>

<item>
<title>UFC 257 Early Prelims</title>
<link>https://aparat.cam/vtmxjn8d9ec9/UFC.257.Early.Prelims.720p.WEB-DL.H264.Fight-BB.mp4.html</link>
<thumbnail>https://i.imgur.com/ztwIAR2.jpg</thumbnail>
<fanart></fanart>
</item>

<item>
<title>WWE Friday Night Smackdown 22-01-2021</title>
<link>https://aparat.cam/wyqwpfsxrz26/WWE.Friday.Night.SmackDown.22nd.Jan.2021.WEBRip.h264-TJ.mp4.html</link>
<thumbnail>https://i.imgur.com/YlG6aSU.jpg</thumbnail>
<fanart></fanart>
</item>

<item>
<title>WWE NXT 20-01-2021</title>
<link>https://aparat.cam/x1l2gpxt6kvc/WWE.NXT.20th.Jan.2021.720p.WEBRip.h264-TJ.mp4.html</link>
<thumbnail>https://i.imgur.com/t6K8GGX.png</thumbnail>
<fanart></fanart>
</item>

<item>
<title>AEW Dynamite 20-01-2021</title>
<link>https://aparat.cam/shsd7b3llxoi/AEW.Dynamite.2021.01.20.720p.WEB.h264-HEEL.mp4.html</link>
<thumbnail>https://i.imgur.com/9j1nbt0.jpg</thumbnail>
<fanart></fanart>
</item>

<item>
<title>UFC On ESPN 20 Main Card</title>
<link>https://aparat.cam/w9p2z1wjegn1/UFC.Fight.Night.Chiesa.vs.Magny.WEB-DL.H264.Fight-BB.mp4.html</link>
<thumbnail>https://i.imgur.com/OZ6kWeb.jpg</thumbnail>
<fanart></fanart>
</item>

<item>
<title>UFC On ESPN 20 Prelims</title>
<link>https://aparat.cam/xjvbw380c2ts/UFC.on.ESPN.20.Preliminary.HDTV.x264-Star.mp4.html</link>
<thumbnail>https://i.imgur.com/OZ6kWeb.jpg</thumbnail>
<fanart></fanart>
</item>

<item>
<title>AEW DARK 19-01-2021</title>
<link>https://aparat.cam/4jzoyuluxzlr/AEW_DARK_19th_Jan_2021_WEBRip_h264-TJ_5Beztv.re_5D.mp4.html</link>
<thumbnail>https://i.imgur.com/bRWA2CJ.png</thumbnail>
<fanart></fanart>
</item>

<item>
<title>WWE Monday Night Raw 18-01-2021</title>
<link>https://aparat.cam/n7s55yem60g2</link>
<thumbnail>https://i.imgur.com/LD14wVD.jpg</thumbnail>
<fanart></fanart>
</item>
